{
 "generated_at": "2026-07-17T09:24:13.626449+09:00",
 "generated_label": "2026.07.17 09:24",
 "gurus": [
  {
   "cik": "1067983",
   "entity": "BERKSHIRE HATHAWAY INC",
   "name_ko": "버크셔 해서웨이",
   "person": "워런 버핏",
   "tagline": "가치투자의 제왕 — 영원한 복리 기계",
   "period": "2026-03-31",
   "period_label": "2026년 1분기",
   "filed": "2026-05-15",
   "total_b": 263.1,
   "positions": 29,
   "holdings": [
    {
     "name": "Apple Inc",
     "pct": 22.0,
     "value_b": 57.84,
     "chg": "―"
    },
    {
     "name": "American Express Co",
     "pct": 17.4,
     "value_b": 45.86,
     "chg": "―"
    },
    {
     "name": "Coca Cola Co",
     "pct": 11.6,
     "value_b": 30.42,
     "chg": "―"
    },
    {
     "name": "Bank America Corp",
     "pct": 9.5,
     "value_b": 25.04,
     "chg": "―"
    },
    {
     "name": "Chevron Corporation",
     "pct": 6.6,
     "value_b": 17.46,
     "chg": "-35%"
    },
    {
     "name": "Occidental Pete Corp",
     "pct": 6.5,
     "value_b": 17.22,
     "chg": "―"
    },
    {
     "name": "Alphabet Inc",
     "pct": 5.9,
     "value_b": 15.6,
     "chg": "+204%"
    },
    {
     "name": "Chubb Ltd Switz",
     "pct": 4.2,
     "value_b": 11.16,
     "chg": "―"
    },
    {
     "name": "Moodys Corp",
     "pct": 4.1,
     "value_b": 10.76,
     "chg": "―"
    },
    {
     "name": "Kraft Heinz Co",
     "pct": 2.8,
     "value_b": 7.32,
     "chg": "―"
    },
    {
     "name": "Davita Inc",
     "pct": 1.8,
     "value_b": 4.63,
     "chg": "-5%"
    },
    {
     "name": "Kroger Co",
     "pct": 1.4,
     "value_b": 3.62,
     "chg": "―"
    },
    {
     "name": "Siriusxm Holdings Inc",
     "pct": 1.1,
     "value_b": 2.88,
     "chg": "―"
    },
    {
     "name": "Delta Air Lines Inc",
     "pct": 1.0,
     "value_b": 2.65,
     "chg": "NEW"
    },
    {
     "name": "Verisign Inc",
     "pct": 0.8,
     "value_b": 2.23,
     "chg": "―"
    }
   ],
   "exits": [
    "Visa Inc",
    "Mastercard Incorporated"
   ]
  },
  {
   "cik": "1037389",
   "entity": "RENAISSANCE TECHNOLOGIES LLC",
   "name_ko": "르네상스 테크놀로지",
   "person": "짐 시몬스 (설립)",
   "tagline": "수학이 시장을 이긴다 — 퀀트의 정점",
   "period": "2026-03-31",
   "period_label": "2026년 1분기",
   "filed": "2026-05-14",
   "total_b": 63.9,
   "positions": 3213,
   "holdings": [
    {
     "name": "United Therapeutics Corp Del",
     "pct": 1.7,
     "value_b": 1.06,
     "chg": "-6%"
    },
    {
     "name": "Palantir Technologies Inc",
     "pct": 1.6,
     "value_b": 1.02,
     "chg": "-21%"
    },
    {
     "name": "Apple Inc",
     "pct": 1.2,
     "value_b": 0.78,
     "chg": "NEW"
    },
    {
     "name": "Kinross Gold Corp",
     "pct": 1.2,
     "value_b": 0.78,
     "chg": "+2%"
    },
    {
     "name": "Micron Technology Inc",
     "pct": 1.1,
     "value_b": 0.73,
     "chg": "-28%"
    },
    {
     "name": "Verisign Inc",
     "pct": 1.1,
     "value_b": 0.7,
     "chg": "+1%"
    },
    {
     "name": "Exelixis Inc",
     "pct": 0.9,
     "value_b": 0.59,
     "chg": "-1%"
    },
    {
     "name": "Franco Nev Corp",
     "pct": 0.9,
     "value_b": 0.55,
     "chg": "-10%"
    },
    {
     "name": "Sandisk Corp",
     "pct": 0.8,
     "value_b": 0.51,
     "chg": "-34%"
    },
    {
     "name": "Nvidia Corporation",
     "pct": 0.7,
     "value_b": 0.44,
     "chg": "+190%"
    },
    {
     "name": "Chevron Corporation",
     "pct": 0.7,
     "value_b": 0.42,
     "chg": "-8%"
    },
    {
     "name": "Roblox Corp",
     "pct": 0.6,
     "value_b": 0.4,
     "chg": "+8%"
    },
    {
     "name": "Carvana Co",
     "pct": 0.6,
     "value_b": 0.38,
     "chg": "-15%"
    },
    {
     "name": "Wayfair Inc",
     "pct": 0.6,
     "value_b": 0.37,
     "chg": "-8%"
    },
    {
     "name": "Robinhood Mkts Inc",
     "pct": 0.6,
     "value_b": 0.35,
     "chg": "+49%"
    }
   ],
   "exits": [
    "Procter And Gamble Co"
   ]
  },
  {
   "cik": "1536411",
   "entity": "Duquesne Family Office LLC",
   "name_ko": "듀케인 패밀리 오피스",
   "person": "스탠리 드러켄밀러",
   "tagline": "45년 무손실 연도의 전설 — 매크로의 거장",
   "period": "2026-03-31",
   "period_label": "2026년 1분기",
   "filed": "2026-05-15",
   "total_b": 0.0,
   "positions": 70,
   "holdings": [
    {
     "name": "Natera Inc",
     "pct": 18.1,
     "value_b": 0.0,
     "chg": "+22%"
    },
    {
     "name": "Insmed Inc",
     "pct": 5.6,
     "value_b": 0.0,
     "chg": "-22%"
    },
    {
     "name": "Taiwan Semiconductor Manufac",
     "pct": 5.0,
     "value_b": 0.0,
     "chg": "-9%"
    },
    {
     "name": "Ishares Inc (CALL)",
     "pct": 4.8,
     "value_b": 0.0,
     "chg": "―"
    },
    {
     "name": "Invesco Exchange Traded Fd T (CALL)",
     "pct": 4.7,
     "value_b": 0.0,
     "chg": "NEW"
    },
    {
     "name": "Ypf Sociedad Anonima",
     "pct": 4.4,
     "value_b": 0.0,
     "chg": "+433%"
    },
    {
     "name": "Ishares Inc",
     "pct": 3.9,
     "value_b": 0.0,
     "chg": "-3%"
    },
    {
     "name": "Bbb Foods Inc",
     "pct": 3.3,
     "value_b": 0.0,
     "chg": "+16%"
    },
    {
     "name": "Alcoa Corp",
     "pct": 2.9,
     "value_b": 0.0,
     "chg": "+9%"
    },
    {
     "name": "Newamsterdam Pharma Company",
     "pct": 2.9,
     "value_b": 0.0,
     "chg": "―"
    },
    {
     "name": "Sea Ltd",
     "pct": 2.7,
     "value_b": 0.0,
     "chg": "+17%"
    },
    {
     "name": "Stmicroelectronics N V",
     "pct": 2.7,
     "value_b": 0.0,
     "chg": "+238%"
    },
    {
     "name": "Woodward Inc",
     "pct": 2.2,
     "value_b": 0.0,
     "chg": "-64%"
    },
    {
     "name": "Teva Pharmaceutical Inds Ltd",
     "pct": 2.1,
     "value_b": 0.0,
     "chg": "-60%"
    },
    {
     "name": "Roku Inc",
     "pct": 2.1,
     "value_b": 0.0,
     "chg": "+29%"
    }
   ],
   "exits": [
    "Select Sector Spdr Tr",
    "Invesco Exchange Traded Fd T",
    "Alphabet Inc"
   ]
  },
  {
   "cik": "1088875",
   "entity": "BAILLIE GIFFORD & CO",
   "name_ko": "베일리 기포드",
   "person": "스코틀랜드 장기 성장주 명가",
   "tagline": "10년 뒤 세상을 바꿀 기업에만 투자",
   "period": "2026-03-31",
   "period_label": "2026년 1분기",
   "filed": "2026-05-08",
   "total_b": 97.9,
   "positions": 271,
   "holdings": [
    {
     "name": "Nvidia",
     "pct": 7.3,
     "value_b": 7.11,
     "chg": "-7%"
    },
    {
     "name": "Amazon.Com",
     "pct": 6.0,
     "value_b": 5.85,
     "chg": "-4%"
    },
    {
     "name": "Mercadolibre",
     "pct": 5.7,
     "value_b": 5.59,
     "chg": "-7%"
    },
    {
     "name": "Spotify Technology Sa",
     "pct": 4.1,
     "value_b": 3.99,
     "chg": "-1%"
    },
    {
     "name": "Nu Holdings Ltd.",
     "pct": 3.6,
     "value_b": 3.54,
     "chg": "-4%"
    },
    {
     "name": "Shopify 'A'",
     "pct": 3.5,
     "value_b": 3.44,
     "chg": "-7%"
    },
    {
     "name": "Cloudflare Inc",
     "pct": 3.4,
     "value_b": 3.29,
     "chg": "-5%"
    },
    {
     "name": "Sea Ltd Adr",
     "pct": 3.4,
     "value_b": 3.28,
     "chg": "+2%"
    },
    {
     "name": "Pdd Holdings Inc",
     "pct": 3.0,
     "value_b": 2.9,
     "chg": "-9%"
    },
    {
     "name": "Applovin",
     "pct": 2.7,
     "value_b": 2.67,
     "chg": "+9%"
    },
    {
     "name": "Meta Platforms Inc",
     "pct": 2.4,
     "value_b": 2.35,
     "chg": "-7%"
    },
    {
     "name": "Coupang",
     "pct": 2.3,
     "value_b": 2.28,
     "chg": "-17%"
    },
    {
     "name": "Netflix Inc",
     "pct": 2.1,
     "value_b": 2.1,
     "chg": "-41%"
    },
    {
     "name": "Samsara",
     "pct": 1.9,
     "value_b": 1.82,
     "chg": "+21%"
    },
    {
     "name": "Microsoft",
     "pct": 1.5,
     "value_b": 1.44,
     "chg": "-30%"
    }
   ],
   "exits": []
  },
  {
   "cik": "949509",
   "entity": "OAKTREE CAPITAL MANAGEMENT LP",
   "name_ko": "오크트리 캐피털",
   "person": "하워드 막스",
   "tagline": "시장 사이클과 위험의 대가",
   "period": "2026-03-31",
   "period_label": "2026년 1분기",
   "filed": "2026-05-15",
   "total_b": 6.3,
   "positions": 142,
   "holdings": [
    {
     "name": "Torm Plc",
     "pct": 10.7,
     "value_b": 0.68,
     "chg": "-10%"
    },
    {
     "name": "Expand Energy Corp",
     "pct": 9.1,
     "value_b": 0.57,
     "chg": "+3%"
    },
    {
     "name": "Invesco Qqq Trust Series 1 (PUT)",
     "pct": 5.2,
     "value_b": 0.33,
     "chg": "NEW"
    },
    {
     "name": "Anglogold Ashanti Plc",
     "pct": 5.0,
     "value_b": 0.31,
     "chg": "-16%"
    },
    {
     "name": "Garrett Motion Inc",
     "pct": 4.2,
     "value_b": 0.27,
     "chg": "-15%"
    },
    {
     "name": "State Street Spdr S&P Oil & Gas Exploration & Production Etf (PUT)",
     "pct": 2.9,
     "value_b": 0.18,
     "chg": "NEW"
    },
    {
     "name": "Telephone And Data Systems Inc",
     "pct": 2.9,
     "value_b": 0.18,
     "chg": "+16%"
    },
    {
     "name": "Viper Energy Inc",
     "pct": 2.8,
     "value_b": 0.18,
     "chg": "-40%"
    },
    {
     "name": "Core Scientific Inc",
     "pct": 2.2,
     "value_b": 0.14,
     "chg": "+13%"
    },
    {
     "name": "Sunopta Inc",
     "pct": 2.1,
     "value_b": 0.13,
     "chg": "―"
    },
    {
     "name": "Petroleo Brasileiro Sa - Petrobras",
     "pct": 2.0,
     "value_b": 0.13,
     "chg": "NEW"
    },
    {
     "name": "Barrick Mining Corp",
     "pct": 1.7,
     "value_b": 0.11,
     "chg": "-12%"
    },
    {
     "name": "Talen Energy Corp",
     "pct": 1.7,
     "value_b": 0.11,
     "chg": "―"
    },
    {
     "name": "Liberty Global Ltd",
     "pct": 1.6,
     "value_b": 0.1,
     "chg": "―"
    },
    {
     "name": "Itau Unibanco Holding Sa",
     "pct": 1.6,
     "value_b": 0.1,
     "chg": "-12%"
    }
   ],
   "exits": [
    "Vaneck Semiconductor Etf",
    "State Street Corp",
    "Indivior Pharmaceuticals Inc",
    "Ftai Aviation Ltd"
   ]
  },
  {
   "cik": "1350694",
   "entity": "Bridgewater Associates, LP",
   "name_ko": "브리지워터",
   "person": "레이 달리오 (설립)",
   "tagline": "세계 최대 헤지펀드 — 올웨더의 창시",
   "period": "2026-03-31",
   "period_label": "2026년 1분기",
   "filed": "2026-05-15",
   "total_b": 22.4,
   "positions": 993,
   "holdings": [
    {
     "name": "State Str Spdr S&P 500 Etf T",
     "pct": 12.7,
     "value_b": 2.84,
     "chg": "-2%"
    },
    {
     "name": "Ishares Tr",
     "pct": 7.8,
     "value_b": 1.75,
     "chg": "-36%"
    },
    {
     "name": "Amazon Com Inc",
     "pct": 4.1,
     "value_b": 0.91,
     "chg": "+125%"
    },
    {
     "name": "Nvidia Corporation",
     "pct": 3.7,
     "value_b": 0.82,
     "chg": "+21%"
    },
    {
     "name": "Alphabet Inc",
     "pct": 2.6,
     "value_b": 0.57,
     "chg": "+26%"
    },
    {
     "name": "Broadcom Inc",
     "pct": 2.5,
     "value_b": 0.57,
     "chg": "+57%"
    },
    {
     "name": "Micron Technology Inc",
     "pct": 2.2,
     "value_b": 0.5,
     "chg": "+66%"
    },
    {
     "name": "Microsoft Corp",
     "pct": 1.8,
     "value_b": 0.4,
     "chg": "+10%"
    },
    {
     "name": "Ge Vernova Inc",
     "pct": 1.7,
     "value_b": 0.38,
     "chg": "-35%"
    },
    {
     "name": "Taiwan Semiconductor Manufac",
     "pct": 1.6,
     "value_b": 0.36,
     "chg": "NEW"
    },
    {
     "name": "Lam Research Corp",
     "pct": 1.5,
     "value_b": 0.34,
     "chg": "-48%"
    },
    {
     "name": "Advanced Micro Devices Inc",
     "pct": 1.2,
     "value_b": 0.26,
     "chg": "-22%"
    },
    {
     "name": "Newmont Corp",
     "pct": 1.1,
     "value_b": 0.25,
     "chg": "―"
    },
    {
     "name": "Oracle Corp",
     "pct": 1.0,
     "value_b": 0.23,
     "chg": "-15%"
    },
    {
     "name": "Ishares Inc",
     "pct": 1.0,
     "value_b": 0.22,
     "chg": "-15%"
    }
   ],
   "exits": [
    "Salesforce Inc"
   ]
  },
  {
   "cik": "1336528",
   "entity": "Pershing Square Capital Management, L.P.",
   "name_ko": "퍼싱 스퀘어",
   "person": "빌 애크먼",
   "tagline": "집중투자 행동주의의 아이콘",
   "period": "2026-03-31",
   "period_label": "2026년 1분기",
   "filed": "2026-05-15",
   "total_b": 13.7,
   "positions": 11,
   "holdings": [
    {
     "name": "Brookfield Corp",
     "pct": 17.6,
     "value_b": 2.42,
     "chg": "-3%"
    },
    {
     "name": "Amazon Com Inc",
     "pct": 17.4,
     "value_b": 2.39,
     "chg": "+19%"
    },
    {
     "name": "Uber Technologies Inc",
     "pct": 15.7,
     "value_b": 2.15,
     "chg": "―"
    },
    {
     "name": "Microsoft Corp",
     "pct": 15.3,
     "value_b": 2.09,
     "chg": "NEW"
    },
    {
     "name": "Restaurant Brands Intl Inc",
     "pct": 12.2,
     "value_b": 1.67,
     "chg": "―"
    },
    {
     "name": "Meta Platforms Inc",
     "pct": 11.1,
     "value_b": 1.52,
     "chg": "―"
    },
    {
     "name": "Howard Hughes Holdings Inc",
     "pct": 8.7,
     "value_b": 1.19,
     "chg": "―"
    },
    {
     "name": "Seaport Entmt Group Inc",
     "pct": 0.8,
     "value_b": 0.11,
     "chg": "―"
    },
    {
     "name": "Alphabet Inc",
     "pct": 0.7,
     "value_b": 0.09,
     "chg": "-95%"
    },
    {
     "name": "Hertz Global Hldgs Inc",
     "pct": 0.5,
     "value_b": 0.07,
     "chg": "―"
    },
    {
     "name": "Alphabet Inc",
     "pct": 0.1,
     "value_b": 0.01,
     "chg": "-95%"
    }
   ],
   "exits": [
    "Hilton Worldwide Hldgs Inc"
   ]
  },
  {
   "cik": "1656456",
   "entity": "Appaloosa LP",
   "name_ko": "아팔루사",
   "person": "데이비드 테퍼",
   "tagline": "위기에서 사는 남자 — 역발상 매크로",
   "period": "2026-03-31",
   "period_label": "2026년 1분기",
   "filed": "2026-05-15",
   "total_b": 5.9,
   "positions": 31,
   "holdings": [
    {
     "name": "Amazon Com Inc",
     "pct": 15.2,
     "value_b": 0.9,
     "chg": "+98%"
    },
    {
     "name": "Micron Technology Inc",
     "pct": 9.5,
     "value_b": 0.56,
     "chg": "+11%"
    },
    {
     "name": "Alphabet Inc",
     "pct": 8.4,
     "value_b": 0.5,
     "chg": "-3%"
    },
    {
     "name": "Uber Technologies Inc",
     "pct": 7.7,
     "value_b": 0.46,
     "chg": "+242%"
    },
    {
     "name": "Taiwan Semiconductor Manufac",
     "pct": 7.6,
     "value_b": 0.45,
     "chg": "+17%"
    },
    {
     "name": "Alibaba Group Hldg Ltd",
     "pct": 7.3,
     "value_b": 0.43,
     "chg": "-33%"
    },
    {
     "name": "Vistra Corp",
     "pct": 5.1,
     "value_b": 0.3,
     "chg": "+114%"
    },
    {
     "name": "Ishares Inc",
     "pct": 5.0,
     "value_b": 0.3,
     "chg": "+28%"
    },
    {
     "name": "Nvidia Corporation",
     "pct": 4.3,
     "value_b": 0.26,
     "chg": "-13%"
    },
    {
     "name": "Nrg Energy Inc",
     "pct": 4.3,
     "value_b": 0.25,
     "chg": "+6%"
    },
    {
     "name": "Meta Platforms Inc",
     "pct": 4.2,
     "value_b": 0.25,
     "chg": "-27%"
    },
    {
     "name": "Sandisk Corp",
     "pct": 3.0,
     "value_b": 0.18,
     "chg": "NEW"
    },
    {
     "name": "Corning Inc",
     "pct": 2.6,
     "value_b": 0.15,
     "chg": "-28%"
    },
    {
     "name": "Whirlpool Corp",
     "pct": 1.8,
     "value_b": 0.11,
     "chg": "-50%"
    },
    {
     "name": "Pdd Holdings Inc",
     "pct": 1.5,
     "value_b": 0.09,
     "chg": "-49%"
    }
   ],
   "exits": [
    "American Airls Group Inc"
   ]
  },
  {
   "cik": "1029160",
   "entity": "SOROS FUND MANAGEMENT LLC",
   "name_ko": "소로스 펀드",
   "person": "조지 소로스",
   "tagline": "영란은행을 무너뜨린 반사성 이론",
   "period": "2026-03-31",
   "period_label": "2026년 1분기",
   "filed": "2026-05-15",
   "total_b": 9.1,
   "positions": 263,
   "holdings": [
    {
     "name": "State Str Spdr S&P 500 Etf T (PUT)",
     "pct": 8.5,
     "value_b": 0.77,
     "chg": "+692%"
    },
    {
     "name": "Amazon Com Inc",
     "pct": 4.4,
     "value_b": 0.41,
     "chg": "-18%"
    },
    {
     "name": "Select Sector Spdr Tr (PUT)",
     "pct": 3.3,
     "value_b": 0.3,
     "chg": "+36%"
    },
    {
     "name": "Coreweave Inc (PUT)",
     "pct": 2.4,
     "value_b": 0.22,
     "chg": "+65%"
    },
    {
     "name": "Global Pmts Inc",
     "pct": 2.4,
     "value_b": 0.22,
     "chg": "+27%"
    },
    {
     "name": "Spdr Series Trust (PUT)",
     "pct": 2.4,
     "value_b": 0.22,
     "chg": "-64%"
    },
    {
     "name": "Electronic Arts Inc",
     "pct": 2.2,
     "value_b": 0.2,
     "chg": "+125%"
    },
    {
     "name": "Nvidia Corporation",
     "pct": 2.1,
     "value_b": 0.19,
     "chg": "+61%"
    },
    {
     "name": "Bill Holdings Inc",
     "pct": 2.0,
     "value_b": 0.19,
     "chg": "+132%"
    },
    {
     "name": "Pg&E Corp",
     "pct": 2.0,
     "value_b": 0.18,
     "chg": "+31%"
    },
    {
     "name": "Taiwan Semiconductor Manufac",
     "pct": 1.9,
     "value_b": 0.18,
     "chg": "+49%"
    },
    {
     "name": "Alphabet Inc",
     "pct": 1.8,
     "value_b": 0.17,
     "chg": "-10%"
    },
    {
     "name": "Jazz Investments I Ltd",
     "pct": 1.7,
     "value_b": 0.16,
     "chg": "-13%"
    },
    {
     "name": "Rivian Automotive Inc",
     "pct": 1.7,
     "value_b": 0.15,
     "chg": "―"
    },
    {
     "name": "Jd.Com Inc",
     "pct": 1.6,
     "value_b": 0.15,
     "chg": "+266%"
    }
   ],
   "exits": [
    "Spotify Usa Inc",
    "Confluent Inc",
    "Dropbox Inc"
   ]
  },
  {
   "cik": "921669",
   "entity": "ICAHN CARL C",
   "name_ko": "칼 아이칸",
   "person": "행동주의의 원조",
   "tagline": "월가가 가장 두려워한 이름",
   "period": "2026-03-31",
   "period_label": "2026년 1분기",
   "filed": "2026-05-15",
   "total_b": 8.6,
   "positions": 12,
   "holdings": [
    {
     "name": "Icahn Enterprises Lp",
     "pct": 48.5,
     "value_b": 4.15,
     "chg": "―"
    },
    {
     "name": "Cvr Energy Inc",
     "pct": 28.0,
     "value_b": 2.4,
     "chg": "+1%"
    },
    {
     "name": "Cvr Partners, Lp",
     "pct": 6.2,
     "value_b": 0.53,
     "chg": "―"
    },
    {
     "name": "Centuri Holdings, Inc.",
     "pct": 4.9,
     "value_b": 0.42,
     "chg": "―"
    },
    {
     "name": "International Flavors And Fragrances Inc.",
     "pct": 3.6,
     "value_b": 0.31,
     "chg": "―"
    },
    {
     "name": "Echostar Corporation",
     "pct": 1.9,
     "value_b": 0.16,
     "chg": "-58%"
    },
    {
     "name": "American Electric Power Company",
     "pct": 1.8,
     "value_b": 0.16,
     "chg": "―"
    },
    {
     "name": "Jetblue Airways Corp.",
     "pct": 1.7,
     "value_b": 0.15,
     "chg": "―"
    },
    {
     "name": "Monro, Inc.",
     "pct": 1.0,
     "value_b": 0.08,
     "chg": "―"
    },
    {
     "name": "Sandridge Energy, Inc.",
     "pct": 0.9,
     "value_b": 0.08,
     "chg": "―"
    },
    {
     "name": "Caesars Entertainment, Inc.",
     "pct": 0.8,
     "value_b": 0.06,
     "chg": "―"
    },
    {
     "name": "Bausch Plus Lomb Corp.",
     "pct": 0.7,
     "value_b": 0.06,
     "chg": "―"
    }
   ],
   "exits": [
    "Southwest Gas Holdings Inc."
   ]
  },
  {
   "cik": "1791786",
   "entity": "Elliott Investment Management L.P.",
   "name_ko": "엘리엇",
   "person": "폴 싱어",
   "tagline": "국가와도 싸우는 행동주의 제국",
   "period": "2026-03-31",
   "period_label": "2026년 1분기",
   "filed": "2026-05-15",
   "total_b": 20.1,
   "positions": 33,
   "holdings": [
    {
     "name": "Triple Flag Precious Metal",
     "pct": 23.0,
     "value_b": 4.63,
     "chg": "―"
    },
    {
     "name": "Phillips 66",
     "pct": 17.4,
     "value_b": 3.51,
     "chg": "―"
    },
    {
     "name": "Suncor Energy Inc New",
     "pct": 17.3,
     "value_b": 3.48,
     "chg": "―"
    },
    {
     "name": "Select Sector Spdr Tr (PUT)",
     "pct": 6.0,
     "value_b": 1.21,
     "chg": "―"
    },
    {
     "name": "Southwest Airls Co",
     "pct": 5.7,
     "value_b": 1.14,
     "chg": "-41%"
    },
    {
     "name": "Select Sector Spdr Tr (PUT)",
     "pct": 3.7,
     "value_b": 0.75,
     "chg": "-54%"
    },
    {
     "name": "Hewlett Packard Enterprise C",
     "pct": 3.2,
     "value_b": 0.65,
     "chg": "+47%"
    },
    {
     "name": "Uniti Group Llc",
     "pct": 2.8,
     "value_b": 0.55,
     "chg": "―"
    },
    {
     "name": "Pinterest Inc",
     "pct": 2.6,
     "value_b": 0.51,
     "chg": "―"
    },
    {
     "name": "Select Sector Spdr Tr (PUT)",
     "pct": 2.3,
     "value_b": 0.47,
     "chg": "NEW"
    },
    {
     "name": "Ishares Tr (PUT)",
     "pct": 2.0,
     "value_b": 0.4,
     "chg": "NEW"
    },
    {
     "name": "Digital Rlty Tr Inc (PUT)",
     "pct": 1.3,
     "value_b": 0.27,
     "chg": "+50%"
    },
    {
     "name": "Etsy Inc",
     "pct": 1.2,
     "value_b": 0.25,
     "chg": "―"
    },
    {
     "name": "Norwegian Cruise Line Hldgs",
     "pct": 1.2,
     "value_b": 0.25,
     "chg": "NEW"
    },
    {
     "name": "Invesco Qqq Tr (PUT)",
     "pct": 1.1,
     "value_b": 0.23,
     "chg": "-73%"
    }
   ],
   "exits": [
    "Select Sector Spdr Tr",
    "Invesco Qqq Tr",
    "Nvidia Corporation"
   ]
  },
  {
   "cik": "1040273",
   "entity": "Third Point LLC",
   "name_ko": "서드 포인트",
   "person": "댄 러브",
   "tagline": "날카로운 주주서한의 행동주의자",
   "period": "2026-03-31",
   "period_label": "2026년 1분기",
   "filed": "2026-05-15",
   "total_b": 2.1,
   "positions": 33,
   "holdings": [
    {
     "name": "Amazon Com Inc",
     "pct": 19.4,
     "value_b": 0.4,
     "chg": "-10%"
    },
    {
     "name": "Telephone & Data Sys Inc",
     "pct": 13.3,
     "value_b": 0.28,
     "chg": "-1%"
    },
    {
     "name": "Crh Plc",
     "pct": 9.6,
     "value_b": 0.2,
     "chg": "-27%"
    },
    {
     "name": "Somnigroup International Inc",
     "pct": 8.1,
     "value_b": 0.17,
     "chg": "-33%"
    },
    {
     "name": "Carpenter Technology Corp",
     "pct": 5.9,
     "value_b": 0.12,
     "chg": "-61%"
    },
    {
     "name": "Mastec Inc",
     "pct": 4.9,
     "value_b": 0.1,
     "chg": "-65%"
    },
    {
     "name": "Danaher Corp Del",
     "pct": 4.8,
     "value_b": 0.1,
     "chg": "-12%"
    },
    {
     "name": "Taiwan Semiconductor Manufac",
     "pct": 4.5,
     "value_b": 0.09,
     "chg": "-35%"
    },
    {
     "name": "Api Group Corp",
     "pct": 3.9,
     "value_b": 0.08,
     "chg": "-32%"
    },
    {
     "name": "Live Nation Entertainment In",
     "pct": 3.4,
     "value_b": 0.07,
     "chg": "-73%"
    },
    {
     "name": "Meta Platforms Inc",
     "pct": 2.5,
     "value_b": 0.05,
     "chg": "NEW"
    },
    {
     "name": "Alphabet Inc",
     "pct": 2.4,
     "value_b": 0.05,
     "chg": "NEW"
    },
    {
     "name": "Spdr Gold Tr",
     "pct": 2.0,
     "value_b": 0.04,
     "chg": "NEW"
    },
    {
     "name": "Hut 8 Corp",
     "pct": 2.0,
     "value_b": 0.04,
     "chg": "NEW"
    },
    {
     "name": "Nvidia Corporation",
     "pct": 1.6,
     "value_b": 0.03,
     "chg": "-94%"
    }
   ],
   "exits": [
    "Pg&E Corp",
    "Microsoft Corp",
    "Brookfield Corp",
    "Caseys Gen Stores Inc",
    "Costar Group Inc"
   ]
  },
  {
   "cik": "1079114",
   "entity": "GREENLIGHT CAPITAL INC",
   "name_ko": "그린라이트 캐피털",
   "person": "데이비드 아인혼",
   "tagline": "리먼 붕괴를 예언한 공매도 명가",
   "period": "2023-12-31",
   "period_label": "2023년 4분기",
   "filed": "2024-02-14",
   "total_b": 2.0,
   "positions": 40,
   "holdings": [
    {
     "name": "Green Brick Partners Inc",
     "pct": 28.9,
     "value_b": 0.59,
     "chg": "-8%"
    },
    {
     "name": "Consol Energy Inc New",
     "pct": 10.3,
     "value_b": 0.21,
     "chg": "-12%"
    },
    {
     "name": "Brighthouse Finl Inc",
     "pct": 7.9,
     "value_b": 0.16,
     "chg": "-3%"
    },
    {
     "name": "Kyndryl Hldgs Inc",
     "pct": 6.4,
     "value_b": 0.13,
     "chg": "+14%"
    },
    {
     "name": "Tenet Healthcare Corp",
     "pct": 4.9,
     "value_b": 0.1,
     "chg": "+44%"
    },
    {
     "name": "The Odp Corp",
     "pct": 4.8,
     "value_b": 0.1,
     "chg": "+8%"
    },
    {
     "name": "Alight Inc",
     "pct": 3.8,
     "value_b": 0.08,
     "chg": "NEW"
    },
    {
     "name": "Spdr Gold Tr",
     "pct": 3.6,
     "value_b": 0.07,
     "chg": "-10%"
    },
    {
     "name": "Teck Resources Ltd",
     "pct": 3.2,
     "value_b": 0.07,
     "chg": "+6%"
    },
    {
     "name": "Livanova Plc",
     "pct": 3.1,
     "value_b": 0.06,
     "chg": "+4%"
    },
    {
     "name": "Graphic Packaging Hldg Co",
     "pct": 3.1,
     "value_b": 0.06,
     "chg": "+32%"
    },
    {
     "name": "Weatherford Intl Plc",
     "pct": 2.2,
     "value_b": 0.04,
     "chg": "+6%"
    },
    {
     "name": "Dht Holdings Inc",
     "pct": 1.8,
     "value_b": 0.04,
     "chg": "+87%"
    },
    {
     "name": "Viatris Inc",
     "pct": 1.8,
     "value_b": 0.04,
     "chg": "NEW"
    },
    {
     "name": "First Ctzns Bancshares Inc N",
     "pct": 1.7,
     "value_b": 0.04,
     "chg": "+6%"
    }
   ],
   "exits": [
    "Southwestern Energy Co",
    "Ishares Silver Tr"
   ]
  },
  {
   "cik": "1649339",
   "entity": "Scion Asset Management, LLC",
   "name_ko": "사이언 자산운용",
   "person": "마이클 버리",
   "tagline": "빅쇼트 — 역발상의 화신",
   "period": "2025-09-30",
   "period_label": "2025년 3분기",
   "filed": "2025-11-03",
   "total_b": 1.4,
   "positions": 8,
   "holdings": [
    {
     "name": "Palantir Technologies Inc (PUT)",
     "pct": 66.0,
     "value_b": 0.91,
     "chg": "NEW"
    },
    {
     "name": "Nvidia Corporation (PUT)",
     "pct": 13.5,
     "value_b": 0.19,
     "chg": "NEW"
    },
    {
     "name": "Pfizer Inc (CALL)",
     "pct": 11.1,
     "value_b": 0.15,
     "chg": "NEW"
    },
    {
     "name": "Halliburton Co (CALL)",
     "pct": 4.5,
     "value_b": 0.06,
     "chg": "NEW"
    },
    {
     "name": "Molina Healthcare Inc",
     "pct": 1.7,
     "value_b": 0.02,
     "chg": "NEW"
    },
    {
     "name": "Lululemon Athletica Inc",
     "pct": 1.3,
     "value_b": 0.02,
     "chg": "+100%"
    },
    {
     "name": "Slm Corp",
     "pct": 1.0,
     "value_b": 0.01,
     "chg": "NEW"
    },
    {
     "name": "Bruker Corp",
     "pct": 1.0,
     "value_b": 0.01,
     "chg": "NEW"
    }
   ],
   "exits": [
    "Unitedhealth Group Inc",
    "Regeneron Pharmaceuticals",
    "Lululemon Athletica Inc",
    "Meta Platforms Inc",
    "Lauder Estee Cos Inc"
   ]
  },
  {
   "cik": "1423053",
   "entity": "CITADEL ADVISORS LLC",
   "name_ko": "시타델",
   "person": "켄 그리핀",
   "tagline": "역사상 가장 많이 번 헤지펀드",
   "period": "2026-03-31",
   "period_label": "2026년 1분기",
   "filed": "2026-05-15",
   "total_b": 618.5,
   "positions": 12857,
   "holdings": [
    {
     "name": "State Str Spdr S&P 500 Etf T (PUT)",
     "pct": 3.9,
     "value_b": 24.19,
     "chg": "+28%"
    },
    {
     "name": "Invesco Qqq Tr (PUT)",
     "pct": 3.3,
     "value_b": 20.54,
     "chg": "-2%"
    },
    {
     "name": "State Str Spdr S&P 500 Etf T (CALL)",
     "pct": 2.8,
     "value_b": 17.58,
     "chg": "―"
    },
    {
     "name": "Tesla Inc (CALL)",
     "pct": 2.2,
     "value_b": 13.53,
     "chg": "-17%"
    },
    {
     "name": "Nvidia Corporation (CALL)",
     "pct": 1.9,
     "value_b": 11.67,
     "chg": "-14%"
    },
    {
     "name": "Invesco Qqq Tr (CALL)",
     "pct": 1.8,
     "value_b": 11.25,
     "chg": "-13%"
    },
    {
     "name": "Tesla Inc (PUT)",
     "pct": 1.5,
     "value_b": 9.45,
     "chg": "-21%"
    },
    {
     "name": "Spdr Gold Tr (CALL)",
     "pct": 1.5,
     "value_b": 9.43,
     "chg": "+15%"
    },
    {
     "name": "Nvidia Corporation (PUT)",
     "pct": 1.5,
     "value_b": 9.01,
     "chg": "-6%"
    },
    {
     "name": "Apple Inc (CALL)",
     "pct": 1.3,
     "value_b": 8.08,
     "chg": "―"
    },
    {
     "name": "Meta Platforms Inc (CALL)",
     "pct": 1.2,
     "value_b": 7.61,
     "chg": "-12%"
    },
    {
     "name": "Microsoft Corp (CALL)",
     "pct": 1.1,
     "value_b": 7.02,
     "chg": "+52%"
    },
    {
     "name": "Micron Technology Inc (PUT)",
     "pct": 0.9,
     "value_b": 5.65,
     "chg": "+36%"
    },
    {
     "name": "Spdr Gold Tr (PUT)",
     "pct": 0.9,
     "value_b": 5.31,
     "chg": "+14%"
    },
    {
     "name": "Amazon Com Inc (CALL)",
     "pct": 0.9,
     "value_b": 5.28,
     "chg": "+9%"
    }
   ],
   "exits": []
  },
  {
   "cik": "1273087",
   "entity": "MILLENNIUM MANAGEMENT LLC",
   "name_ko": "밀레니엄",
   "person": "이지 잉글랜더",
   "tagline": "멀티매니저 팟 시스템의 완성형",
   "period": "2026-03-31",
   "period_label": "2026년 1분기",
   "filed": "2026-05-15",
   "total_b": 240.3,
   "positions": 5622,
   "holdings": [
    {
     "name": "Ishares Tr (PUT)",
     "pct": 4.1,
     "value_b": 9.96,
     "chg": "+31%"
    },
    {
     "name": "Ishares Tr",
     "pct": 3.5,
     "value_b": 8.48,
     "chg": "-10%"
    },
    {
     "name": "Nvidia Corporation (PUT)",
     "pct": 1.7,
     "value_b": 4.12,
     "chg": "―"
    },
    {
     "name": "Invesco Qqq Tr (PUT)",
     "pct": 1.5,
     "value_b": 3.49,
     "chg": "-31%"
    },
    {
     "name": "Ishares Tr (CALL)",
     "pct": 1.2,
     "value_b": 2.97,
     "chg": "-24%"
    },
    {
     "name": "Microsoft Corp (PUT)",
     "pct": 1.1,
     "value_b": 2.55,
     "chg": "+61%"
    },
    {
     "name": "Invesco Qqq Tr (CALL)",
     "pct": 1.0,
     "value_b": 2.29,
     "chg": "+9%"
    },
    {
     "name": "Amazon Com Inc (PUT)",
     "pct": 0.9,
     "value_b": 2.28,
     "chg": "+16%"
    },
    {
     "name": "Apple Inc (PUT)",
     "pct": 0.9,
     "value_b": 2.21,
     "chg": "-3%"
    },
    {
     "name": "Meta Platforms Inc (PUT)",
     "pct": 0.9,
     "value_b": 2.07,
     "chg": "+14%"
    },
    {
     "name": "Alphabet Inc (PUT)",
     "pct": 0.8,
     "value_b": 1.89,
     "chg": "+21%"
    },
    {
     "name": "Nvidia Corporation",
     "pct": 0.8,
     "value_b": 1.85,
     "chg": "-31%"
    },
    {
     "name": "Tesla Inc (PUT)",
     "pct": 0.8,
     "value_b": 1.83,
     "chg": "+69%"
    },
    {
     "name": "State Str Spdr S&P 500 Etf T (PUT)",
     "pct": 0.7,
     "value_b": 1.78,
     "chg": "―"
    },
    {
     "name": "Spdr Series Trust",
     "pct": 0.7,
     "value_b": 1.65,
     "chg": "NEW"
    }
   ],
   "exits": []
  },
  {
   "cik": "1009207",
   "entity": "D. E. Shaw & Co., Inc.",
   "name_ko": "D.E. 쇼",
   "person": "데이비드 쇼 (설립)",
   "tagline": "계산과학이 만든 퀀트 명가",
   "period": "2026-03-31",
   "period_label": "2026년 1분기",
   "filed": "2026-05-15",
   "total_b": 166.3,
   "positions": 4470,
   "holdings": [
    {
     "name": "Nvidia Corporation",
     "pct": 1.5,
     "value_b": 2.56,
     "chg": "-37%"
    },
    {
     "name": "Microsoft Corp",
     "pct": 1.4,
     "value_b": 2.28,
     "chg": "-10%"
    },
    {
     "name": "Broadcom Inc",
     "pct": 1.2,
     "value_b": 2.02,
     "chg": "+127%"
    },
    {
     "name": "Alphabet Inc",
     "pct": 1.2,
     "value_b": 1.97,
     "chg": "+76%"
    },
    {
     "name": "Apple Inc",
     "pct": 1.1,
     "value_b": 1.77,
     "chg": "+28%"
    },
    {
     "name": "Tesla Inc",
     "pct": 1.0,
     "value_b": 1.62,
     "chg": "+88%"
    },
    {
     "name": "Boston Scientific Corp",
     "pct": 0.9,
     "value_b": 1.53,
     "chg": "+116%"
    },
    {
     "name": "Alphabet Inc",
     "pct": 0.9,
     "value_b": 1.43,
     "chg": "+144%"
    },
    {
     "name": "Home Depot Inc",
     "pct": 0.7,
     "value_b": 1.24,
     "chg": "+50%"
    },
    {
     "name": "Micron Technology Inc",
     "pct": 0.7,
     "value_b": 1.24,
     "chg": "+9%"
    },
    {
     "name": "Western Digital Corp",
     "pct": 0.7,
     "value_b": 1.09,
     "chg": "-1%"
    },
    {
     "name": "Meta Platforms Inc",
     "pct": 0.6,
     "value_b": 1.08,
     "chg": "+76%"
    },
    {
     "name": "Taiwan Semiconductor Manufac",
     "pct": 0.6,
     "value_b": 1.03,
     "chg": "+4%"
    },
    {
     "name": "Jpmorgan Chase & Co",
     "pct": 0.6,
     "value_b": 1.02,
     "chg": "+725%"
    },
    {
     "name": "Amazon Com Inc",
     "pct": 0.6,
     "value_b": 0.99,
     "chg": "-22%"
    }
   ],
   "exits": []
  },
  {
   "cik": "1179392",
   "entity": "TWO SIGMA INVESTMENTS, LP",
   "name_ko": "투시그마",
   "person": "데이터 사이언스 헤지펀드",
   "tagline": "머신러닝으로 시장을 읽다",
   "period": "2026-03-31",
   "period_label": "2026년 1분기",
   "filed": "2026-05-15",
   "total_b": 123.9,
   "positions": 4546,
   "holdings": [
    {
     "name": "Nvidia Corporation",
     "pct": 1.6,
     "value_b": 1.96,
     "chg": "+832%"
    },
    {
     "name": "Apple Inc",
     "pct": 1.2,
     "value_b": 1.51,
     "chg": "+567%"
    },
    {
     "name": "Amazon Com Inc",
     "pct": 1.1,
     "value_b": 1.32,
     "chg": "+452%"
    },
    {
     "name": "Alphabet Inc",
     "pct": 1.0,
     "value_b": 1.27,
     "chg": "+16686%"
    },
    {
     "name": "Tesla Inc",
     "pct": 0.9,
     "value_b": 1.08,
     "chg": "+413%"
    },
    {
     "name": "Jpmorgan Chase & Co",
     "pct": 0.8,
     "value_b": 0.97,
     "chg": "+734%"
    },
    {
     "name": "Palantir Technologies Inc",
     "pct": 0.8,
     "value_b": 0.94,
     "chg": "+311%"
    },
    {
     "name": "Costco Wholesale Corporation",
     "pct": 0.7,
     "value_b": 0.87,
     "chg": "+238%"
    },
    {
     "name": "Tjx Cos Inc New",
     "pct": 0.7,
     "value_b": 0.84,
     "chg": "+212%"
    },
    {
     "name": "Mastercard Incorporated",
     "pct": 0.7,
     "value_b": 0.84,
     "chg": "+279%"
    },
    {
     "name": "T-Mobile Us Inc",
     "pct": 0.7,
     "value_b": 0.82,
     "chg": "+229%"
    },
    {
     "name": "Lockheed Martin Corp",
     "pct": 0.7,
     "value_b": 0.82,
     "chg": "+178%"
    },
    {
     "name": "Berkshire Hathaway Inc Del",
     "pct": 0.6,
     "value_b": 0.78,
     "chg": "+275%"
    },
    {
     "name": "Micron Technology Inc",
     "pct": 0.6,
     "value_b": 0.77,
     "chg": "+120%"
    },
    {
     "name": "Adobe Inc",
     "pct": 0.6,
     "value_b": 0.76,
     "chg": "+322%"
    }
   ],
   "exits": []
  },
  {
   "cik": "1603466",
   "entity": "Point72 Asset Management, L.P.",
   "name_ko": "포인트72",
   "person": "스티브 코헨",
   "tagline": "전설의 트레이더가 세운 멀티전략",
   "period": "2026-03-31",
   "period_label": "2026년 1분기",
   "filed": "2026-05-15",
   "total_b": 78.1,
   "positions": 3704,
   "holdings": [
    {
     "name": "Nvidia Corporation",
     "pct": 1.7,
     "value_b": 1.32,
     "chg": "-24%"
    },
    {
     "name": "Amazon Com Inc",
     "pct": 1.3,
     "value_b": 1.03,
     "chg": "-6%"
    },
    {
     "name": "Arista Networks Inc",
     "pct": 1.0,
     "value_b": 0.8,
     "chg": "-13%"
    },
    {
     "name": "State Str Spdr S&P 500 Etf T (CALL)",
     "pct": 1.0,
     "value_b": 0.8,
     "chg": "-28%"
    },
    {
     "name": "State Str Spdr S&P 500 Etf T (PUT)",
     "pct": 1.0,
     "value_b": 0.8,
     "chg": "-52%"
    },
    {
     "name": "Asml Hldg Nv",
     "pct": 1.0,
     "value_b": 0.75,
     "chg": "-4%"
    },
    {
     "name": "Credo Technology Group Holdi",
     "pct": 0.9,
     "value_b": 0.7,
     "chg": "+34%"
    },
    {
     "name": "Broadcom Inc",
     "pct": 0.9,
     "value_b": 0.7,
     "chg": "-21%"
    },
    {
     "name": "Invesco Qqq Tr (PUT)",
     "pct": 0.9,
     "value_b": 0.68,
     "chg": "-46%"
    },
    {
     "name": "Teradyne Inc",
     "pct": 0.9,
     "value_b": 0.68,
     "chg": "-19%"
    },
    {
     "name": "Taiwan Semiconductor Manufac",
     "pct": 0.8,
     "value_b": 0.63,
     "chg": "-60%"
    },
    {
     "name": "Applied Matls Inc",
     "pct": 0.8,
     "value_b": 0.59,
     "chg": "+260%"
    },
    {
     "name": "Equinix Inc",
     "pct": 0.7,
     "value_b": 0.52,
     "chg": "-31%"
    },
    {
     "name": "Meta Platforms Inc",
     "pct": 0.7,
     "value_b": 0.52,
     "chg": "+1272%"
    },
    {
     "name": "Spotify Technology S A",
     "pct": 0.6,
     "value_b": 0.44,
     "chg": "-6%"
    }
   ],
   "exits": []
  },
  {
   "cik": "1167483",
   "entity": "TIGER GLOBAL MANAGEMENT LLC",
   "name_ko": "타이거 글로벌",
   "person": "체이스 콜먼",
   "tagline": "타이거 컵스의 대표주자 — 테크 성장주",
   "period": "2026-03-31",
   "period_label": "2026년 1분기",
   "filed": "2026-05-15",
   "total_b": 22.8,
   "positions": 54,
   "holdings": [
    {
     "name": "Alphabet Inc",
     "pct": 13.4,
     "value_b": 3.06,
     "chg": "―"
    },
    {
     "name": "Nvidia Corporation",
     "pct": 9.2,
     "value_b": 2.09,
     "chg": "+9%"
    },
    {
     "name": "Amazon Com Inc",
     "pct": 9.1,
     "value_b": 2.08,
     "chg": "―"
    },
    {
     "name": "Taiwan Semiconductor Manufac",
     "pct": 8.2,
     "value_b": 1.88,
     "chg": "+49%"
    },
    {
     "name": "Meta Platforms Inc",
     "pct": 7.7,
     "value_b": 1.77,
     "chg": "+12%"
    },
    {
     "name": "Sea Ltd",
     "pct": 5.6,
     "value_b": 1.28,
     "chg": "―"
    },
    {
     "name": "Broadcom Inc",
     "pct": 4.9,
     "value_b": 1.11,
     "chg": "+25%"
    },
    {
     "name": "Microsoft Corp",
     "pct": 4.1,
     "value_b": 0.93,
     "chg": "-54%"
    },
    {
     "name": "Ge Vernova Inc",
     "pct": 3.7,
     "value_b": 0.85,
     "chg": "―"
    },
    {
     "name": "Lam Research Corp",
     "pct": 3.6,
     "value_b": 0.83,
     "chg": "―"
    },
    {
     "name": "Spotify Technology S A",
     "pct": 3.4,
     "value_b": 0.77,
     "chg": "+25%"
    },
    {
     "name": "Coupang Inc",
     "pct": 2.9,
     "value_b": 0.65,
     "chg": "+32%"
    },
    {
     "name": "Applied Matls Inc",
     "pct": 2.5,
     "value_b": 0.57,
     "chg": "+85%"
    },
    {
     "name": "Corpay Inc",
     "pct": 2.2,
     "value_b": 0.51,
     "chg": "―"
    },
    {
     "name": "Applovin Corp",
     "pct": 1.7,
     "value_b": 0.4,
     "chg": "-23%"
    }
   ],
   "exits": [
    "Flutter Entmt Plc"
   ]
  },
  {
   "cik": "1135730",
   "entity": "COATUE MANAGEMENT LLC",
   "name_ko": "코아추",
   "person": "필리프 라퐁",
   "tagline": "기술주 크로스오버 투자의 강자",
   "period": "2026-03-31",
   "period_label": "2026년 1분기",
   "filed": "2026-05-15",
   "total_b": 29.1,
   "positions": 62,
   "holdings": [
    {
     "name": "Taiwan Semiconductor Manufac",
     "pct": 10.8,
     "value_b": 3.14,
     "chg": "+8%"
    },
    {
     "name": "Ge Vernova Inc",
     "pct": 7.7,
     "value_b": 2.25,
     "chg": "-24%"
    },
    {
     "name": "Lam Research Corp",
     "pct": 7.4,
     "value_b": 2.15,
     "chg": "+2%"
    },
    {
     "name": "Applied Matls Inc",
     "pct": 6.2,
     "value_b": 1.79,
     "chg": "-12%"
    },
    {
     "name": "Broadcom Inc",
     "pct": 5.9,
     "value_b": 1.7,
     "chg": "―"
    },
    {
     "name": "Eaton Corp Plc",
     "pct": 5.8,
     "value_b": 1.7,
     "chg": "―"
    },
    {
     "name": "Amazon Com Inc",
     "pct": 5.7,
     "value_b": 1.65,
     "chg": "-20%"
    },
    {
     "name": "Meta Platforms Inc",
     "pct": 5.5,
     "value_b": 1.61,
     "chg": "-26%"
    },
    {
     "name": "Constellation Energy Corp",
     "pct": 4.5,
     "value_b": 1.29,
     "chg": "-22%"
    },
    {
     "name": "Alphabet Inc",
     "pct": 4.3,
     "value_b": 1.24,
     "chg": "-37%"
    },
    {
     "name": "Nvidia Corporation",
     "pct": 3.8,
     "value_b": 1.1,
     "chg": "-31%"
    },
    {
     "name": "Equinix Inc",
     "pct": 3.7,
     "value_b": 1.07,
     "chg": "NEW"
    },
    {
     "name": "Microsoft Corp",
     "pct": 3.2,
     "value_b": 0.92,
     "chg": "-52%"
    },
    {
     "name": "Netflix Inc.",
     "pct": 2.3,
     "value_b": 0.66,
     "chg": "-37%"
    },
    {
     "name": "Asml Hldg Nv",
     "pct": 2.3,
     "value_b": 0.66,
     "chg": "NEW"
    }
   ],
   "exits": []
  },
  {
   "cik": "1061165",
   "entity": "LONE PINE CAPITAL LLC",
   "name_ko": "론 파인",
   "person": "스티븐 만델 (설립)",
   "tagline": "타이거 컵스 — 펀더멘털 성장주 장인",
   "period": "2026-03-31",
   "period_label": "2026년 1분기",
   "filed": "2026-05-15",
   "total_b": 12.5,
   "positions": 36,
   "holdings": [
    {
     "name": "Vistra Corp",
     "pct": 7.4,
     "value_b": 0.93,
     "chg": "+19%"
    },
    {
     "name": "Asml Hldg Nv",
     "pct": 6.9,
     "value_b": 0.87,
     "chg": "+8%"
    },
    {
     "name": "Carpenter Technology Corp",
     "pct": 5.7,
     "value_b": 0.72,
     "chg": "+38%"
    },
    {
     "name": "Lpl Finl Hldgs Inc",
     "pct": 4.9,
     "value_b": 0.62,
     "chg": "-1%"
    },
    {
     "name": "Applovin Corp",
     "pct": 4.6,
     "value_b": 0.58,
     "chg": "+88%"
    },
    {
     "name": "Talen Energy Corp",
     "pct": 4.6,
     "value_b": 0.58,
     "chg": "+41%"
    },
    {
     "name": "Teradyne Inc",
     "pct": 4.4,
     "value_b": 0.56,
     "chg": "NEW"
    },
    {
     "name": "Carvana Co",
     "pct": 4.4,
     "value_b": 0.55,
     "chg": "-1%"
    },
    {
     "name": "Nu Hldgs Ltd",
     "pct": 4.4,
     "value_b": 0.55,
     "chg": "+28%"
    },
    {
     "name": "Medline Inc",
     "pct": 4.2,
     "value_b": 0.52,
     "chg": "―"
    },
    {
     "name": "Corning Inc",
     "pct": 4.0,
     "value_b": 0.51,
     "chg": "NEW"
    },
    {
     "name": "Clean Harbors Inc",
     "pct": 4.0,
     "value_b": 0.5,
     "chg": "+27%"
    },
    {
     "name": "Mastec Inc",
     "pct": 3.9,
     "value_b": 0.49,
     "chg": "NEW"
    },
    {
     "name": "Taiwan Semiconductor Manufac",
     "pct": 3.7,
     "value_b": 0.47,
     "chg": "-54%"
    },
    {
     "name": "Brookfield Corp",
     "pct": 3.6,
     "value_b": 0.45,
     "chg": "-30%"
    }
   ],
   "exits": [
    "Broadcom Inc",
    "Microsoft Corp",
    "Doordash Inc",
    "Amazon Com Inc"
   ]
  },
  {
   "cik": "1103804",
   "entity": "VIKING GLOBAL INVESTORS LP",
   "name_ko": "바이킹 글로벌",
   "person": "안드레아스 할보르센",
   "tagline": "타이거 컵스 — 롱숏의 교과서",
   "period": "2026-03-31",
   "period_label": "2026년 1분기",
   "filed": "2026-05-15",
   "total_b": 35.7,
   "positions": 77,
   "holdings": [
    {
     "name": "Visa Inc",
     "pct": 5.4,
     "value_b": 1.91,
     "chg": "+59%"
    },
    {
     "name": "Taiwan Semiconductor Manufac",
     "pct": 4.2,
     "value_b": 1.51,
     "chg": "-9%"
    },
    {
     "name": "Schwab Charles Corp",
     "pct": 3.9,
     "value_b": 1.38,
     "chg": "+6%"
    },
    {
     "name": "Disney Walt Co",
     "pct": 3.6,
     "value_b": 1.28,
     "chg": "+19%"
    },
    {
     "name": "Fortive Corp",
     "pct": 3.5,
     "value_b": 1.24,
     "chg": "+17%"
    },
    {
     "name": "Air Products And Chemicals I",
     "pct": 3.3,
     "value_b": 1.19,
     "chg": "-14%"
    },
    {
     "name": "Mcdonalds Corp",
     "pct": 3.2,
     "value_b": 1.13,
     "chg": "―"
    },
    {
     "name": "Sherwin Williams Co",
     "pct": 2.8,
     "value_b": 1.0,
     "chg": "-2%"
    },
    {
     "name": "Tesla Inc",
     "pct": 2.6,
     "value_b": 0.93,
     "chg": "+47%"
    },
    {
     "name": "Apple Inc",
     "pct": 2.6,
     "value_b": 0.91,
     "chg": "NEW"
    },
    {
     "name": "Bridgebio Pharma Inc",
     "pct": 2.5,
     "value_b": 0.88,
     "chg": "-18%"
    },
    {
     "name": "Carvana Co",
     "pct": 2.4,
     "value_b": 0.87,
     "chg": "+162%"
    },
    {
     "name": "Microsoft Corp",
     "pct": 2.4,
     "value_b": 0.85,
     "chg": "-28%"
    },
    {
     "name": "Thermo Fisher Scientific Inc",
     "pct": 2.3,
     "value_b": 0.82,
     "chg": "+110%"
    },
    {
     "name": "Jpmorgan Chase & Co",
     "pct": 2.2,
     "value_b": 0.8,
     "chg": "+42%"
    }
   ],
   "exits": [
    "Advanced Micro Devices Inc"
   ]
  },
  {
   "cik": "1647251",
   "entity": "TCI Fund Management Ltd",
   "name_ko": "TCI 펀드",
   "person": "크리스 혼",
   "tagline": "초집중 포트폴리오의 유럽 거인",
   "period": "2026-03-31",
   "period_label": "2026년 1분기",
   "filed": "2026-05-15",
   "total_b": 45.2,
   "positions": 10,
   "holdings": [
    {
     "name": "Ge Aerospace",
     "pct": 29.8,
     "value_b": 13.48,
     "chg": "―"
    },
    {
     "name": "Visa Inc",
     "pct": 20.4,
     "value_b": 9.21,
     "chg": "+10%"
    },
    {
     "name": "Moodys Corp",
     "pct": 13.8,
     "value_b": 6.25,
     "chg": "+8%"
    },
    {
     "name": "S&P Global Inc",
     "pct": 13.2,
     "value_b": 5.97,
     "chg": "+19%"
    },
    {
     "name": "Canadian Pacific Kansas City",
     "pct": 8.1,
     "value_b": 3.66,
     "chg": "-2%"
    },
    {
     "name": "Alphabet Inc",
     "pct": 5.6,
     "value_b": 2.54,
     "chg": "+17%"
    },
    {
     "name": "Ferrovial Se",
     "pct": 2.9,
     "value_b": 1.33,
     "chg": "―"
    },
    {
     "name": "Canadian Natl Ry Co",
     "pct": 2.2,
     "value_b": 1.01,
     "chg": "―"
    },
    {
     "name": "Microsoft Corp",
     "pct": 2.2,
     "value_b": 1.01,
     "chg": "-84%"
    },
    {
     "name": "Alphabet Inc",
     "pct": 1.6,
     "value_b": 0.71,
     "chg": "NEW"
    }
   ],
   "exits": []
  },
  {
   "cik": "1697748",
   "entity": "ARK Investment Management LLC",
   "name_ko": "아크 인베스트",
   "person": "캐시 우드",
   "tagline": "파괴적 혁신에 올인하는 낙관주의",
   "period": "2026-03-31",
   "period_label": "2026년 1분기",
   "filed": "2026-05-12",
   "total_b": 12.9,
   "positions": 182,
   "holdings": [
    {
     "name": "Tesla Inc",
     "pct": 8.2,
     "value_b": 1.05,
     "chg": "-3%"
    },
    {
     "name": "Advanced Micro Devices Inc",
     "pct": 4.3,
     "value_b": 0.55,
     "chg": "+5%"
    },
    {
     "name": "Crispr Therapeutics Ag",
     "pct": 4.2,
     "value_b": 0.54,
     "chg": "+8%"
    },
    {
     "name": "Shopify Inc",
     "pct": 3.9,
     "value_b": 0.5,
     "chg": "+5%"
    },
    {
     "name": "Palantir Technologies Inc",
     "pct": 3.5,
     "value_b": 0.45,
     "chg": "-4%"
    },
    {
     "name": "Tempus Ai Inc",
     "pct": 3.4,
     "value_b": 0.43,
     "chg": "+27%"
    },
    {
     "name": "Circle Internet Group Inc",
     "pct": 3.3,
     "value_b": 0.43,
     "chg": "+9%"
    },
    {
     "name": "Robinhood Markets Inc",
     "pct": 3.2,
     "value_b": 0.42,
     "chg": "+25%"
    },
    {
     "name": "Coinbase Global Inc",
     "pct": 3.2,
     "value_b": 0.41,
     "chg": "-7%"
    },
    {
     "name": "Teradyne Inc",
     "pct": 2.9,
     "value_b": 0.37,
     "chg": "-47%"
    },
    {
     "name": "Roku Inc",
     "pct": 2.8,
     "value_b": 0.36,
     "chg": "-35%"
    },
    {
     "name": "Roblox Corp",
     "pct": 2.6,
     "value_b": 0.33,
     "chg": "+22%"
    },
    {
     "name": "Twist Bioscience Corp",
     "pct": 2.3,
     "value_b": 0.3,
     "chg": "-16%"
    },
    {
     "name": "Beam Therapeutics Inc",
     "pct": 2.2,
     "value_b": 0.29,
     "chg": "-3%"
    },
    {
     "name": "Amazon.Com Inc",
     "pct": 2.2,
     "value_b": 0.28,
     "chg": "+12%"
    }
   ],
   "exits": []
  },
  {
   "cik": "1541617",
   "entity": "Altimeter Capital Management, LP",
   "name_ko": "알티미터",
   "person": "브래드 거스트너",
   "tagline": "실리콘밸리와 가장 가까운 투자자",
   "period": "2026-03-31",
   "period_label": "2026년 1분기",
   "filed": "2026-05-15",
   "total_b": 5.7,
   "positions": 13,
   "holdings": [
    {
     "name": "Nvidia Corporation",
     "pct": 28.6,
     "value_b": 1.63,
     "chg": "+15%"
    },
    {
     "name": "Meta Platforms Inc",
     "pct": 19.6,
     "value_b": 1.12,
     "chg": "+6%"
    },
    {
     "name": "Uber Technologies Inc",
     "pct": 10.1,
     "value_b": 0.57,
     "chg": "+43%"
    },
    {
     "name": "Taiwan Semiconductor Mfg Ltd",
     "pct": 8.1,
     "value_b": 0.46,
     "chg": "+12%"
    },
    {
     "name": "Microsoft Corp",
     "pct": 7.7,
     "value_b": 0.44,
     "chg": "-7%"
    },
    {
     "name": "Amazon Com Inc",
     "pct": 7.6,
     "value_b": 0.44,
     "chg": "-6%"
    },
    {
     "name": "Coreweave Inc",
     "pct": 6.1,
     "value_b": 0.35,
     "chg": "+40%"
    },
    {
     "name": "Snowflake Inc",
     "pct": 5.1,
     "value_b": 0.29,
     "chg": "-5%"
    },
    {
     "name": "Arm Holdings Plc",
     "pct": 4.6,
     "value_b": 0.26,
     "chg": "NEW"
    },
    {
     "name": "Axon Enterprise Inc",
     "pct": 1.1,
     "value_b": 0.06,
     "chg": "NEW"
    },
    {
     "name": "Robinhood Mkts Inc",
     "pct": 1.1,
     "value_b": 0.06,
     "chg": "-30%"
    },
    {
     "name": "Broadcom Inc",
     "pct": 0.4,
     "value_b": 0.02,
     "chg": "+109%"
    },
    {
     "name": "Grab Holdings Limited",
     "pct": 0.0,
     "value_b": 0.0,
     "chg": "―"
    }
   ],
   "exits": [
    "Coupang Inc",
    "Confluent Inc",
    "Alphabet Inc",
    "Zillow Group Inc",
    "Mercadolibre Inc"
   ]
  },
  {
   "cik": "850529",
   "entity": "Fisher Asset Management, LLC",
   "name_ko": "피셔 인베스트먼트",
   "person": "켄 피셔",
   "tagline": "슈퍼 스톡스 — 초대형 자산운용",
   "period": "2026-03-31",
   "period_label": "2026년 1분기",
   "filed": "2026-05-05",
   "total_b": 294.9,
   "positions": 1016,
   "holdings": [
    {
     "name": "Nvidia Corp Com",
     "pct": 5.2,
     "value_b": 15.44,
     "chg": "+3%"
    },
    {
     "name": "Apple Inc",
     "pct": 4.9,
     "value_b": 14.32,
     "chg": "+2%"
    },
    {
     "name": "Ishares Tr 7 10Yr Tr Bd Etf",
     "pct": 4.8,
     "value_b": 14.03,
     "chg": "+9%"
    },
    {
     "name": "Alphabet Inc Class A",
     "pct": 3.8,
     "value_b": 11.23,
     "chg": "+2%"
    },
    {
     "name": "Microsoft Corp",
     "pct": 3.3,
     "value_b": 9.6,
     "chg": "+3%"
    },
    {
     "name": "Vanguard Fds Int Term Corp",
     "pct": 2.5,
     "value_b": 7.38,
     "chg": "+6%"
    },
    {
     "name": "Amazon Com Inc Com",
     "pct": 2.4,
     "value_b": 7.12,
     "chg": "+2%"
    },
    {
     "name": "Caterpillar Inc",
     "pct": 2.3,
     "value_b": 6.93,
     "chg": "+3%"
    },
    {
     "name": "Taiwan Semiconductor Manuf Adr",
     "pct": 2.1,
     "value_b": 6.29,
     "chg": "+3%"
    },
    {
     "name": "Asml Hldg Nv Nys",
     "pct": 2.1,
     "value_b": 6.08,
     "chg": "+3%"
    },
    {
     "name": "Goldman Sachs Group Inc",
     "pct": 2.0,
     "value_b": 5.78,
     "chg": "―"
    },
    {
     "name": "Exxon Mobil Corp",
     "pct": 1.9,
     "value_b": 5.48,
     "chg": "+2%"
    },
    {
     "name": "Walmart Inc",
     "pct": 1.7,
     "value_b": 5.09,
     "chg": "―"
    },
    {
     "name": "Jpmorgan Chase Co",
     "pct": 1.7,
     "value_b": 5.01,
     "chg": "+6%"
    },
    {
     "name": "Broadcom Inc Com",
     "pct": 1.5,
     "value_b": 4.55,
     "chg": "+6%"
    }
   ],
   "exits": []
  }
 ]
}